repetita_parser/__init__.py
repetita_parser/demands.py
repetita_parser/errors.py
repetita_parser/instance.py
repetita_parser/topology.py
repetita_parser/types.py
repetita_parser/utils.py
tests/data/export/instance/.gitignore
tests/data/export/instance/exported.demands
tests/data/export/instance/exported.graph
repetita_parser-5.0.0.dist-info/METADATA
repetita_parser-5.0.0.dist-info/WHEEL
repetita_parser-5.0.0.dist-info/licenses/LICENSE
repetita_parser-5.0.0.dist-info/RECORD
