Metadata-Version: 2.4
Name: repetita-parser
Version: 5.0.0
Summary: A parser for the REPETITA format
Project-URL: Documentation, https://github.com/leon-richardt/python-repetita-parser#readme
Project-URL: Issues, https://github.com/leon-richardt/python-repetita-parser/issues
Project-URL: Source, https://github.com/leon-richardt/python-repetita-parser
Author-email: Leon Richardt <pip@leon.dev>
License-Expression: MIT
License-File: LICENSE
Requires-Python: >=3.7
Requires-Dist: numpy
Provides-Extra: networkx
Requires-Dist: networkx; extra == 'networkx'
